flask_security_headers/__init__.py
flask_security_headers/security.py
flask_security_headers-1.0.3.dist-info/licenses/LICENSE
flask_security_headers-1.0.3.dist-info/METADATA
flask_security_headers-1.0.3.dist-info/WHEEL
flask_security_headers-1.0.3.dist-info/top_level.txt
flask_security_headers-1.0.3.dist-info/RECORD
